Workbook

Sheet Dashboard
B2: SALES PERFORMANCE DASHBOARD | Q2: ="Updated " & TEXT(TODAY(),"mmm d, yyyy") -> Updated May 14, 2026
B3: FY 2024–2025 • 24 months • 8 regions • 10 products • 10 reps | Q3: Auto-refreshing from Data / Regions / Products / Reps
B6: TOTAL REVENUE | E6: VS TARGET | H6: GROSS MARGIN | K6: YoY GROWTH | N6: BEST MONTH | Q6: REPS OVER QUOTA
B7: =SUM(Data!B2:B25) -> 2810853 | E7: =SUM(Data!B2:B25)/SUM(Data!C2:C25)-1 -> 0.092017483 | H7: =SUM(Data!E2:E25)/SUM(Data!B2:B25) -> 0.45006018 | K7: =SUM(Data!B14:B25)/SUM(Data!B2:B13)-1 -> -0.011704746 | N7: =TEXT(INDEX(Data!A2:A25,MATCH(MAX(Data!B2:B25),Data!B2:B25,0)),"mmm-yy") -> Dec-24 | Q7: =COUNTIF(Reps!E2:E11,">=1")&" / "&COUNTA(Reps!A2:A11) -> 7 / 10
B9: ="Avg $"&TEXT(AVERAGE(Data!B2:B25),"#,##0")&" / month" -> Avg $117,119 / month | E9: =IF(SUM(Data!B2:B25)-SUM(Data!C2:C25)>=0,"+$","-$")&TEXT(ABS(SUM(Data!B2:B25)-SUM(Data!C2:C25)),"#,##0")&" vs plan" -> +$236,853 vs plan | H9: ="$"&TEXT(SUM(Data!E2:E25),"#,##0")&" gross profit" -> $1,265,053 gross profit | K9: ="FY25 $"&TEXT(SUM(Data!B14:B25),"#,##0") -> FY25 $1,397,153 | N9: ="$"&TEXT(MAX(Data!B2:B25),"#,##0")&" peak revenue" -> $156,800 peak revenue | Q9: ="Avg attainment "&TEXT(AVERAGE(Reps!E2:E11),"0.0%") -> Avg attainment 112.3%
B11: REVENUE TREND — 24 MONTHS | K11: MONTHLY PERFORMANCE DETAIL
K12: Month | L12: Revenue | M12: Target | N12: Variance | O12: Var % | P12: Margin | Q12: Status
K13: =TEXT(Data!A14,"mmm-yy") -> Jan-25 | L13: =Data!B14 -> 121905 | M13: =Data!C14 -> 108000 | N13: =L13-M13 -> 13905 | O13: =IFERROR(N13/M13,0) -> 0.12875 | P13: =IFERROR((Data!B14-Data!D14)/Data!B14,0) -> 0.4503917 | Q13: =IF(O13>=0.05,"▲ Strong",IF(O13>=0,"● On track","▼ Below")) -> ▲ Strong
K14: =TEXT(Data!A15,"mmm-yy") -> Feb-25 | L14: =Data!B15 -> 89296 | M14: =Data!C15 -> 109500 | N14: =L14-M14 -> -20204 | O14: =IFERROR(N14/M14,0) -> -0.18451142 | P14: =IFERROR((Data!B15-Data!D15)/Data!B15,0) -> 0.45014334 | Q14: =IF(O14>=0.05,"▲ Strong",IF(O14>=0,"● On track","▼ Below")) -> ▼ Below
K15: =TEXT(Data!A16,"mmm-yy") -> Mar-25 | L15: =Data!B16 -> 85639 | M15: =Data!C16 -> 111000 | N15: =L15-M15 -> -25361 | O15: =IFERROR(N15/M15,0) -> -0.22847748 | P15: =IFERROR((Data!B16-Data!D16)/Data!B16,0) -> 0.45001693 | Q15: =IF(O15>=0.05,"▲ Strong",IF(O15>=0,"● On track","▼ Below")) -> ▼ Below
K16: =TEXT(Data!A17,"mmm-yy") -> Apr-25 | L16: =Data!B17 -> 134598 | M16: =Data!C17 -> 112500 | N16: =L16-M16 -> 22098 | O16: =IFERROR(N16/M16,0) -> 0.19642667 | P16: =IFERROR((Data!B17-Data!D17)/Data!B17,0) -> 0.45021471 | Q16: =IF(O16>=0.05,"▲ Strong",IF(O16>=0,"● On track","▼ Below")) -> ▲ Strong
K17: =TEXT(Data!A18,"mmm-yy") -> May-25 | L17: =Data!B18 -> 106024 | M17: =Data!C18 -> 114000 | N17: =L17-M17 -> -7976 | O17: =IFERROR(N17/M17,0) -> -0.069964912 | P17: =IFERROR((Data!B18-Data!D18)/Data!B18,0) -> 0.4501245 | Q17: =IF(O17>=0.05,"▲ Strong",IF(O17>=0,"● On track","▼ Below")) -> ▼ Below
K18: =TEXT(Data!A19,"mmm-yy") -> Jun-25 | L18: =Data!B19 -> 106049 | M18: =Data!C19 -> 115500 | N18: =L18-M18 -> -9451 | O18: =IFERROR(N18/M18,0) -> -0.08182684 | P18: =IFERROR((Data!B19-Data!D19)/Data!B19,0) -> 0.45025413 | Q18: =IF(O18>=0.05,"▲ Strong",IF(O18>=0,"● On track","▼ Below")) -> ▼ Below
K19: =TEXT(Data!A20,"mmm-yy") -> Jul-25 | L19: =Data!B20 -> 106628 | M19: =Data!C20 -> 117000 | N19: =L19-M19 -> -10372 | O19: =IFERROR(N19/M19,0) -> -0.088649573 | P19: =IFERROR((Data!B20-Data!D20)/Data!B20,0) -> 0.45042578 | Q19: =IF(O19>=0.05,"▲ Strong",IF(O19>=0,"● On track","▼ Below")) -> ▼ Below
K20: =TEXT(Data!A21,"mmm-yy") -> Aug-25 | L20: =Data!B21 -> 103144 | M20: =Data!C21 -> 118500 | N20: =L20-M20 -> -15356 | O20: =IFERROR(N20/M20,0) -> -0.1295865 | P20: =IFERROR((Data!B21-Data!D21)/Data!B21,0) -> 0.4502831 | Q20: =IF(O20>=0.05,"▲ Strong",IF(O20>=0,"● On track","▼ Below")) -> ▼ Below
K21: =TEXT(Data!A22,"mmm-yy") -> Sept-25 | L21: =Data!B22 -> 144265 | M21: =Data!C22 -> 120000 | N21: =L21-M21 -> 24265 | O21: =IFERROR(N21/M21,0) -> 0.20220833 | P21: =IFERROR((Data!B22-Data!D22)/Data!B22,0) -> 0.45031712 | Q21: =IF(O21>=0.05,"▲ Strong",IF(O21>=0,"● On track","▼ Below")) -> ▲ Strong
K22: =TEXT(Data!A23,"mmm-yy") -> Oct-25 | L22: =Data!B23 -> 104717 | M22: =Data!C23 -> 121500 | N22: =L22-M22 -> -16783 | O22: =IFERROR(N22/M22,0) -> -0.13813169 | P22: =IFERROR((Data!B23-Data!D23)/Data!B23,0) -> 0.44994605 | Q22: =IF(O22>=0.05,"▲ Strong",IF(O22>=0,"● On track","▼ Below")) -> ▼ Below
K23: =TEXT(Data!A24,"mmm-yy") -> Nov-25 | L23: =Data!B24 -> 144348 | M23: =Data!C24 -> 123000 | N23: =L23-M23 -> 21348 | O23: =IFERROR(N23/M23,0) -> 0.17356098 | P23: =IFERROR((Data!B24-Data!D24)/Data!B24,0) -> 0.44994042 | Q23: =IF(O23>=0.05,"▲ Strong",IF(O23>=0,"● On track","▼ Below")) -> ▲ Strong
K24: =TEXT(Data!A25,"mmm-yy") -> Dec-25 | L24: =Data!B25 -> 150540 | M24: =Data!C25 -> 124500 | N24: =L24-M24 -> 26040 | O24: =IFERROR(N24/M24,0) -> 0.20915663 | P24: =IFERROR((Data!B25-Data!D25)/Data!B25,0) -> 0.44998007 | Q24: =IF(O24>=0.05,"▲ Strong",IF(O24>=0,"● On track","▼ Below")) -> ▲ Strong
B30: TOP PRODUCTS BY REVENUE | K30: SALES REP LEADERBOARD
K31: Rank | L31: Sales Rep | M31: Region | N31: Deals | O31: Revenue | P31: Quota | Q31: Status
K32: 1 | L32: =INDEX(Reps!A$2:A$11,MATCH(LARGE(Reps!D$2:D$11,1),Reps!D$2:D$11,0)) -> Sofia Rodriguez | M32: =INDEX(Reps!B$2:B$11,MATCH(LARGE(Reps!D$2:D$11,1),Reps!D$2:D$11,0)) -> North America | N32: =INDEX(Reps!C$2:C$11,MATCH(LARGE(Reps!D$2:D$11,1),Reps!D$2:D$11,0)) -> 156 | O32: =LARGE(Reps!D$2:D$11,1) -> 698200 | P32: =INDEX(Reps!E$2:E$11,MATCH(LARGE(Reps!D$2:D$11,1),Reps!D$2:D$11,0)) -> 1.32 | Q32: =IF(P32>=1,"▲ Hit","▼ Miss") -> ▲ Hit
K33: 2 | L33: =INDEX(Reps!A$2:A$11,MATCH(LARGE(Reps!D$2:D$11,2),Reps!D$2:D$11,0)) -> Ethan Walker | M33: =INDEX(Reps!B$2:B$11,MATCH(LARGE(Reps!D$2:D$11,2),Reps!D$2:D$11,0)) -> North America | N33: =INDEX(Reps!C$2:C$11,MATCH(LARGE(Reps!D$2:D$11,2),Reps!D$2:D$11,0)) -> 148 | O33: =LARGE(Reps!D$2:D$11,2) -> 654100 | P33: =INDEX(Reps!E$2:E$11,MATCH(LARGE(Reps!D$2:D$11,2),Reps!D$2:D$11,0)) -> 1.28 | Q33: =IF(P33>=1,"▲ Hit","▼ Miss") -> ▲ Hit
K34: 3 | L34: =INDEX(Reps!A$2:A$11,MATCH(LARGE(Reps!D$2:D$11,3),Reps!D$2:D$11,0)) -> Ayesha Khan | M34: =INDEX(Reps!B$2:B$11,MATCH(LARGE(Reps!D$2:D$11,3),Reps!D$2:D$11,0)) -> EMEA - West | N34: =INDEX(Reps!C$2:C$11,MATCH(LARGE(Reps!D$2:D$11,3),Reps!D$2:D$11,0)) -> 142 | O34: =LARGE(Reps!D$2:D$11,3) -> 612400 | P34: =INDEX(Reps!E$2:E$11,MATCH(LARGE(Reps!D$2:D$11,3),Reps!D$2:D$11,0)) -> 1.24 | Q34: =IF(P34>=1,"▲ Hit","▼ Miss") -> ▲ Hit
K35: 4 | L35: =INDEX(Reps!A$2:A$11,MATCH(LARGE(Reps!D$2:D$11,4),Reps!D$2:D$11,0)) -> Hana Tanaka | M35: =INDEX(Reps!B$2:B$11,MATCH(LARGE(Reps!D$2:D$11,4),Reps!D$2:D$11,0)) -> APAC - North | N35: =INDEX(Reps!C$2:C$11,MATCH(LARGE(Reps!D$2:D$11,4),Reps!D$2:D$11,0)) -> 134 | O35: =LARGE(Reps!D$2:D$11,4) -> 592800 | P35: =INDEX(Reps!E$2:E$11,MATCH(LARGE(Reps!D$2:D$11,4),Reps!D$2:D$11,0)) -> 1.21 | Q35: =IF(P35>=1,"▲ Hit","▼ Miss") -> ▲ Hit
K36: 5 | L36: =INDEX(Reps!A$2:A$11,MATCH(LARGE(Reps!D$2:D$11,5),Reps!D$2:D$11,0)) -> Marcus Chen | M36: =INDEX(Reps!B$2:B$11,MATCH(LARGE(Reps!D$2:D$11,5),Reps!D$2:D$11,0)) -> APAC - North | N36: =INDEX(Reps!C$2:C$11,MATCH(LARGE(Reps!D$2:D$11,5),Reps!D$2:D$11,0)) -> 128 | O36: =LARGE(Reps!D$2:D$11,5) -> 558900 | P36: =INDEX(Reps!E$2:E$11,MATCH(LARGE(Reps!D$2:D$11,5),Reps!D$2:D$11,0)) -> 1.18 | Q36: =IF(P36>=1,"▲ Hit","▼ Miss") -> ▲ Hit
K37: 6 | L37: =INDEX(Reps!A$2:A$11,MATCH(LARGE(Reps!D$2:D$11,6),Reps!D$2:D$11,0)) -> Priya Sharma | M37: =INDEX(Reps!B$2:B$11,MATCH(LARGE(Reps!D$2:D$11,6),Reps!D$2:D$11,0)) -> APAC - South | N37: =INDEX(Reps!C$2:C$11,MATCH(LARGE(Reps!D$2:D$11,6),Reps!D$2:D$11,0)) -> 118 | O37: =LARGE(Reps!D$2:D$11,6) -> 489700 | P37: =INDEX(Reps!E$2:E$11,MATCH(LARGE(Reps!D$2:D$11,6),Reps!D$2:D$11,0)) -> 1.08 | Q37: =IF(P37>=1,"▲ Hit","▼ Miss") -> ▲ Hit
K38: 7 | L38: =INDEX(Reps!A$2:A$11,MATCH(LARGE(Reps!D$2:D$11,7),Reps!D$2:D$11,0)) -> Zara Ahmed | M38: =INDEX(Reps!B$2:B$11,MATCH(LARGE(Reps!D$2:D$11,7),Reps!D$2:D$11,0)) -> Middle East | N38: =INDEX(Reps!C$2:C$11,MATCH(LARGE(Reps!D$2:D$11,7),Reps!D$2:D$11,0)) -> 115 | O38: =LARGE(Reps!D$2:D$11,7) -> 478300 | P38: =INDEX(Reps!E$2:E$11,MATCH(LARGE(Reps!D$2:D$11,7),Reps!D$2:D$11,0)) -> 1.12 | Q38: =IF(P38>=1,"▲ Hit","▼ Miss") -> ▲ Hit
K39: 8 | L39: =INDEX(Reps!A$2:A$11,MATCH(LARGE(Reps!D$2:D$11,8),Reps!D$2:D$11,0)) -> Carlos Mendoza | M39: =INDEX(Reps!B$2:B$11,MATCH(LARGE(Reps!D$2:D$11,8),Reps!D$2:D$11,0)) -> South America | N39: =INDEX(Reps!C$2:C$11,MATCH(LARGE(Reps!D$2:D$11,8),Reps!D$2:D$11,0)) -> 102 | O39: =LARGE(Reps!D$2:D$11,8) -> 412600 | P39: =INDEX(Reps!E$2:E$11,MATCH(LARGE(Reps!D$2:D$11,8),Reps!D$2:D$11,0)) -> 0.97 | Q39: =IF(P39>=1,"▲ Hit","▼ Miss") -> ▼ Miss
K40: 9 | L40: =INDEX(Reps!A$2:A$11,MATCH(LARGE(Reps!D$2:D$11,9),Reps!D$2:D$11,0)) -> Liam O'Connor | M40: =INDEX(Reps!B$2:B$11,MATCH(LARGE(Reps!D$2:D$11,9),Reps!D$2:D$11,0)) -> EMEA - East | N40: =INDEX(Reps!C$2:C$11,MATCH(LARGE(Reps!D$2:D$11,9),Reps!D$2:D$11,0)) -> 96 | O40: =LARGE(Reps!D$2:D$11,9) -> 358200 | P40: =INDEX(Reps!E$2:E$11,MATCH(LARGE(Reps!D$2:D$11,9),Reps!D$2:D$11,0)) -> 0.89 | Q40: =IF(P40>=1,"▲ Hit","▼ Miss") -> ▼ Miss
K41: 10 | L41: =INDEX(Reps!A$2:A$11,MATCH(LARGE(Reps!D$2:D$11,10),Reps!D$2:D$11,0)) -> Daniel Okafor | M41: =INDEX(Reps!B$2:B$11,MATCH(LARGE(Reps!D$2:D$11,10),Reps!D$2:D$11,0)) -> Africa | N41: =INDEX(Reps!C$2:C$11,MATCH(LARGE(Reps!D$2:D$11,10),Reps!D$2:D$11,0)) -> 89 | O41: =LARGE(Reps!D$2:D$11,10) -> 312500 | P41: =INDEX(Reps!E$2:E$11,MATCH(LARGE(Reps!D$2:D$11,10),Reps!D$2:D$11,0)) -> 0.94 | Q41: =IF(P41>=1,"▲ Hit","▼ Miss") -> ▼ Miss
B47: REGIONAL PERFORMANCE — REVENUE vs TARGET

Sheet Data
A1: Month | B1: Revenue | C1: Target | D1: COGS | E1: Gross Profit
A2: 45292 | B2: 98500 | C2: 90000 | D2: 54000 | E2: =B2-D2 -> 44500
A3: 45323 | B3: 84200 | C3: 91500 | D3: 46500 | E3: =B3-D3 -> 37700
A4: 45352 | B4: 91300 | C4: 93000 | D4: 50200 | E4: =B4-D4 -> 41100
A5: 45383 | B5: 105400 | C5: 94500 | D5: 58000 | E5: =B5-D5 -> 47400
A6: 45413 | B6: 112800 | C6: 96000 | D6: 62000 | E6: =B6-D6 -> 50800
A7: 45444 | B7: 118600 | C7: 97500 | D7: 65300 | E7: =B7-D7 -> 53300
A8: 45474 | B8: 124300 | C8: 99000 | D8: 68400 | E8: =B8-D8 -> 55900
A9: 45505 | B9: 119800 | C9: 100500 | D9: 65900 | E9: =B9-D9 -> 53900
A10: 45536 | B10: 128400 | C10: 102000 | D10: 70600 | E10: =B10-D10 -> 57800
A11: 45566 | B11: 132100 | C11: 103500 | D11: 72700 | E11: =B11-D11 -> 59400
A12: 45597 | B12: 141500 | C12: 105000 | D12: 77800 | E12: =B12-D12 -> 63700
A13: 45627 | B13: 156800 | C13: 106500 | D13: 86200 | E13: =B13-D13 -> 70600
... A25: 45992 | B25: 150540 | C25: 124500 | D25: 82800 | E25: =B25-D25 -> 67740

Sheet Regions
A1: Region | B1: Revenue | C1: Target | D1: Reps
A2: North America | B2: 1245000 | C2: 1150000 | D2: 12
A3: South America | B3: 685000 | C3: 720000 | D3: 7
A4: EMEA - West | B4: 1098000 | C4: 980000 | D4: 14
A5: EMEA - East | B5: 542000 | C5: 580000 | D5: 6
A6: APAC - North | B6: 875000 | C6: 820000 | D6: 9
A7: APAC - South | B7: 612000 | C7: 650000 | D7: 8
A8: Middle East | B8: 428000 | C8: 410000 | D8: 5
A9: Africa | B9: 295000 | C9: 340000 | D9: 4

Sheet Products
A1: Product | B1: Units Sold | C1: Revenue | D1: Margin %
A2: Atlas Pro CRM | B2: 4250 | C2: 892500 | D2: 0.68
A3: Helix Analytics | B3: 3180 | C3: 715500 | D3: 0.72
A4: Nimbus Cloud Suite | B4: 2940 | C4: 661500 | D4: 0.65
A5: Orion Security | B5: 2615 | C5: 588375 | D5: 0.74
A6: Quasar BI | B6: 2480 | C6: 558000 | D6: 0.7
A7: Vertex API Gateway | B7: 2105 | C7: 473625 | D7: 0.66
A8: Polaris Workflow | B8: 1890 | C8: 425250 | D8: 0.63
A9: Cobalt Forms | B9: 1560 | C9: 351000 | D9: 0.58
A10: Falcon Insights | B10: 1340 | C10: 301500 | D10: 0.61
A11: Echo Messenger | B11: 1085 | C11: 244125 | D11: 0.55

Sheet Reps
A1: Sales Rep | B1: Region | C1: Deals Closed | D1: Revenue | E1: Quota Attainment
A2: Ayesha Khan | B2: EMEA - West | C2: 142 | D2: 612400 | E2: 1.24
A3: Marcus Chen | B3: APAC - North | C3: 128 | D3: 558900 | E3: 1.18
A4: Sofia Rodriguez | B4: North America | C4: 156 | D4: 698200 | E4: 1.32
A5: Daniel Okafor | B5: Africa | C5: 89 | D5: 312500 | E5: 0.94
A6: Priya Sharma | B6: APAC - South | C6: 118 | D6: 489700 | E6: 1.08
A7: Liam O'Connor | B7: EMEA - East | C7: 96 | D7: 358200 | E7: 0.89
A8: Hana Tanaka | B8: APAC - North | C8: 134 | D8: 592800 | E8: 1.21
A9: Carlos Mendoza | B9: South America | C9: 102 | D9: 412600 | E9: 0.97
A10: Zara Ahmed | B10: Middle East | C10: 115 | D10: 478300 | E10: 1.12
A11: Ethan Walker | B11: North America | C11: 148 | D11: 654100 | E11: 1.28
